imageClassification/__init__.py
sthefr/__init__.py
sthefreak/__init__.py
sthefreak/imageClassification/__init__.py
sthefreak/imageClassification/dataLoad/__init__.py
sthefreak/imageClassification/dataLoad/loader.py
sthefreak/imageClassification/dataSource/__init__.py
sthefreak/imageClassification/dataSource/collect.py
Sthefreak-0.0.4.dist-info/LICENSE
Sthefreak-0.0.4.dist-info/METADATA
Sthefreak-0.0.4.dist-info/WHEEL
Sthefreak-0.0.4.dist-info/top_level.txt
Sthefreak-0.0.4.dist-info/RECORD
