Metadata-Version: 2.1
Name: Sthefreak
Version: 0.0.4
Summary: A Data Science toolkit
Home-page: UNKNOWN
Author: Suyash Dixit
Author-email: ar-suyash.dixit@rakuten.com
License: UNKNOWN
Platform: UNKNOWN
Requires-Dist: bs4
Requires-Dist: requests
